aiorobonect/__init__.py
aiorobonect/client.py
aiorobonect/const.py
aiorobonect/utils.py
aiorobonect-1.3.1.dist-info/LICENSE
aiorobonect-1.3.1.dist-info/METADATA
aiorobonect-1.3.1.dist-info/WHEEL
aiorobonect-1.3.1.dist-info/top_level.txt
aiorobonect-1.3.1.dist-info/RECORD
