Metadata-Version: 2.1
Name: aiorobonect
Version: 1.3.1
Summary: Module to communicate to the Robonect API
Home-page: https://github.com/geertmeersman/aiorobonect
Author: Geert Meersman
Author-email: geertmeersman@gmail.com
License: MIT
Classifier: Programming Language :: Python :: 3
Classifier: License :: OSI Approved :: Apache Software License
Classifier: Operating System :: OS Independent
License-File: LICENSE
Requires-Dist: aiohttp
Requires-Dist: pip<24.3,>=8.0.3
Requires-Dist: ruff==0.6.7
